AUTHORS.rst
CONTRIBUTING.rst
HISTORY.rst
LICENSE
MANIFEST.in
README.rst
setup.cfg
setup.py
django_planout_experiments.egg-info/PKG-INFO
django_planout_experiments.egg-info/SOURCES.txt
django_planout_experiments.egg-info/dependency_links.txt
django_planout_experiments.egg-info/not-zip-safe
django_planout_experiments.egg-info/requires.txt
django_planout_experiments.egg-info/top_level.txt
planout_experiments/__init__.py
planout_experiments/admin.py
planout_experiments/apps.py
planout_experiments/models.py
planout_experiments/urls.py
planout_experiments/views.py
planout_experiments/wagtail_hooks.py
planout_experiments/migrations/0001_initial.py
planout_experiments/migrations/__init__.py
planout_experiments/static/css/planout_experiments.css
planout_experiments/static/js/planout_experiments.js
planout_experiments/templates/planout_experiments/base.html
planout_experiments/templates/templates/experiments/experiment_detail.html