Metadata-Version: 1.1
Name: django-planout-experiments
Version: 0.1.0
Summary: A Django application that uses Facebook's Planout library to manage product experiments and track outcomes
Home-page: https://github.com/adamhaney/django-planout-experiments
Author: adamjhaney
Author-email: adam.jacob.haney@gmail.com
License: MIT
Keywords: django-planout-experiments
Platform: UNKNOWN
Classifier: Development Status :: 3 - Alpha
Classifier: Framework :: Django :: 2.0
Classifier: Intended Audience :: Developers
Classifier: License :: OSI Approved :: BSD License
Classifier: Natural Language :: English
Classifier: Programming Language :: Python :: 2
Classifier: Programming Language :: Python :: 2.7
Classifier: Programming Language :: Python :: 3
Classifier: Programming Language :: Python :: 3.4
Classifier: Programming Language :: Python :: 3.5
Classifier: Programming Language :: Python :: 3.6
